pywin32supervisor/__init__.py
pywin32supervisor/supervisor.py
pywin32supervisor-0.0.1.dist-info/licenses/LICENSE
tests/__init__.py
tests/test_program.py
tests/test_service.py
tests/test_utils.py
tests/test_xmlrpc.py
pywin32supervisor-0.0.1.dist-info/METADATA
pywin32supervisor-0.0.1.dist-info/WHEEL
pywin32supervisor-0.0.1.dist-info/entry_points.txt
pywin32supervisor-0.0.1.dist-info/top_level.txt
pywin32supervisor-0.0.1.dist-info/RECORD
