Metadata-Version: 2.4
Name: pywin32supervisor
Version: 0.0.1
Summary: Python win32 service similar to supervisor for Unix-based systems.
Author-email: Artillence <greg.karz@artillence.com>
License: MIT License
Project-URL: Homepage, https://github.com/Artillence/pywin32supervisor
Requires-Python: >=3.10
License-File: LICENSE
Requires-Dist: pywin32==308
Requires-Dist: psutil==7.0.0
Provides-Extra: dev
Requires-Dist: ruff==0.9.7; extra == "dev"
Requires-Dist: pre-commit>=4.0.1; extra == "dev"
Requires-Dist: pytest>=7.0.0; extra == "dev"
Requires-Dist: pytest-cov>=4.0.0; extra == "dev"
Dynamic: license-file
